setup.py
ppsspyramidutils/__init__.py
ppsspyramidutils/appsettings.py
ppsspyramidutils/filemanager.py
ppsspyramidutils/modelbase.py
ppsspyramidutils/utils.py
ppsspyramidutils.egg-info/PKG-INFO
ppsspyramidutils.egg-info/SOURCES.txt
ppsspyramidutils.egg-info/dependency_links.txt
ppsspyramidutils.egg-info/top_level.txt