Metadata-Version: 1.0
Name: ppsspyramidutils
Version: 1.3.1
Summary: Simple utils to handle data from ini files in Pyramid
Home-page: UNKNOWN
Author: pdepmcp
Author-email: pdepmcp@gmail.com
License: UNKNOWN
Platform: UNKNOWN
